{
   "abstract" : "Dancer logger engine for Sys::Syslog",
   "author" : [
      "Alexis Sukrieh <sukria@sukria.net>",
      "Yanick Champoux <yanick@cpan.org>"
   ],
   "dynamic_config" : 0,
   "generated_by" : "Dist::Zilla version 4.300030, CPAN::Meta::Converter version 2.120921",
   "license" : [
      "perl_5"
   ],
   "meta-spec" : {
      "url" : "http://search.cpan.org/perldoc?CPAN::Meta::Spec",
      "version" : "2"
   },
   "name" : "Dancer-Logger-Syslog",
   "prereqs" : {
      "build" : {
         "requires" : {
            "Module::Build" : "0.3601"
         }
      },
      "configure" : {
         "requires" : {
            "ExtUtils::MakeMaker" : "6.30",
            "Module::Build" : "0.3601"
         }
      },
      "develop" : {
         "requires" : {
            "Test::CPAN::Meta" : "0",
            "Test::Pod" : "1.41"
         }
      },
      "runtime" : {
         "requires" : {
            "Dancer::Config" : "0",
            "Dancer::Logger::Abstract" : "0",
            "File::Basename" : "0",
            "Sys::Syslog" : "0",
            "base" : "0",
            "strict" : "0",
            "warnings" : "0"
         }
      },
      "test" : {
         "requires" : {
            "Dancer::ModuleLoader" : "0",
            "File::Find" : "0",
            "File::Temp" : "0",
            "Test::More" : "0"
         }
      }
   },
   "provides" : {
      "Dancer::Logger::Syslog" : {
         "file" : "lib/Dancer/Logger/Syslog.pm",
         "version" : "0.5"
      }
   },
   "release_status" : "stable",
   "resources" : {
      "bugtracker" : {
         "web" : "https://github.com/PerlDancer/Dancer-Logger-Syslog/issues"
      },
      "repository" : {
         "url" : "https://github.com/PerlDancer/Dancer-Logger-Syslog"
      }
   },
   "version" : "0.5",
   "x_authority" : "cpan:SUKRIA",
   "x_contributors" : [
      "Sam Crawley <samc@catalyst.net.nz>",
      "Sergey Romanov <complefor@rambler.ru>"
   ]
}

